Wisdom_Data_Library/__init__.py
Wisdom_Data_Library/functions.py
wisdom_data_library-0.1.20.dist-info/licenses/LICENCE
wisdom_data_library-0.1.20.dist-info/METADATA
wisdom_data_library-0.1.20.dist-info/WHEEL
wisdom_data_library-0.1.20.dist-info/top_level.txt
wisdom_data_library-0.1.20.dist-info/RECORD
