Metadata-Version: 2.4
Name: Wisdom_Data_Library
Version: 0.1.20
Summary: This is a help library for Data ETL jobs using notebooks in either Databricks or MS Fabric
Author-email: David Turner <david@wisdomservices.com>
Classifier: Programming Language :: Python :: 3
Classifier: License :: OSI Approved :: MIT License
Classifier: Operating System :: OS Independent
Requires-Python: >=3.7
License-File: LICENCE
Provides-Extra: dev
Requires-Dist: pytest; extra == "dev"
Dynamic: license-file
